etcd3/__init__.py
etcd3/client.py
etcd3/etcdrpc/__init__.py
etcd3/etcdrpc/auth_pb2.py
etcd3/etcdrpc/auth_pb2_grpc.py
etcd3/etcdrpc/kv_pb2.py
etcd3/etcdrpc/kv_pb2_grpc.py
etcd3/etcdrpc/rpc_pb2.py
etcd3/etcdrpc/rpc_pb2_grpc.py
etcd3/events.py
etcd3/exceptions.py
etcd3/leases.py
etcd3/locks.py
etcd3/members.py
etcd3/proto/auth.proto
etcd3/proto/buf.yaml
etcd3/proto/kv.proto
etcd3/proto/rpc.proto
etcd3/transactions.py
etcd3/utils.py
etcd3/watch.py
hippo_etcd3-0.12.0.dist-info/AUTHORS.rst
hippo_etcd3-0.12.0.dist-info/LICENSE
hippo_etcd3-0.12.0.dist-info/METADATA
hippo_etcd3-0.12.0.dist-info/WHEEL
hippo_etcd3-0.12.0.dist-info/RECORD
