Metadata-Version: 2.1
Name: hippo-etcd3
Version: 0.12.0
Summary: etcd3 package used in hippo
Author: Shawn Li
Author-email: shawn@shawnli.org
Requires-Python: >=3.12,<4.0
Classifier: Programming Language :: Python :: 3
Classifier: Programming Language :: Python :: 3.12
Requires-Dist: grpcio (>=1.62.1,<2.0.0)
Requires-Dist: six (>=1.16.0,<2.0.0)
